Metadata-Version: 2.1
Name: onehot
Version: 0.1.3
Summary: One-Hot encoder with sklearn-ish API interface that process mixed string and numeric labels directly.
Home-page: http://github.com/kmedian/onehot
Author: Ulf Hamster
Author-email: 554c46@gmail.com
License: MIT
Platform: UNKNOWN
Requires-Python: >=3.6
